pixelsort/__init__.py
pixelsort/__main__.py
pixelsort/cli.py
pixelsort/image.py
pixelsort_cli-1.1.0.dist-info/licenses/LICENSE
pixelsort_cli-1.1.0.dist-info/METADATA
pixelsort_cli-1.1.0.dist-info/WHEEL
pixelsort_cli-1.1.0.dist-info/entry_points.txt
pixelsort_cli-1.1.0.dist-info/top_level.txt
pixelsort_cli-1.1.0.dist-info/RECORD
