Metadata-Version: 2.4
Name: pixelsort-cli
Version: 1.1.0
Summary: A Python CLI tool for sorting pixels in images.
Author-email: Ferdinand Theil <f.p.theil@proton.me>
License: MIT License
Project-URL: Homepage, https://github.com/Blotz/pixelsort-cli
Project-URL: Bug Tracker, https://github.com/Blotz/pixelsort-cli/issues
Classifier: Programming Language :: Python :: 3
Classifier: Programming Language :: Python :: 3.9
Classifier: Programming Language :: Python :: 3.10
Classifier: Programming Language :: Python :: 3.11
Classifier: Programming Language :: Python :: 3.12
Classifier: Programming Language :: Python :: 3.13
Classifier: License :: OSI Approved :: MIT License
Classifier: Operating System :: OS Independent
Requires-Python: >=3.9
License-File: LICENSE
Requires-Dist: numpy
Requires-Dist: scipy
Requires-Dist: opencv-python
Requires-Dist: filetype
Provides-Extra: test
Requires-Dist: pytest; extra == "test"
Requires-Dist: pytest-xdist; extra == "test"
Dynamic: license-file
